{"nodes": [{"id": "e_\u6d4b\u8bd5_src_tests_utils_export_import_test_ts", "label": "export-import.test.ts", "file_type": "code", "source_file": "E:\\\u6d4b\u8bd5\\src\\__tests__\\utils\\export-import.test.ts", "source_location": "L1"}, {"id": "utils_export_import_test_mockjsontosheet_mockbooknew_mockbookappendsheet_mockwritefile_mockread_mocksheettojson", "label": "{\n  mockJsonToSheet,\n  mockBookNew,\n  mockBookAppendSheet,\n  mockWriteFile,\n  mockRead,\n  mockSheetToJson,\n}", "file_type": "code", "source_file": "E:\\\u6d4b\u8bd5\\src\\__tests__\\utils\\export-import.test.ts", "source_location": "L6"}, {"id": "utils_export_import_test_getcallargs", "label": "getCallArgs()", "file_type": "code", "source_file": "E:\\\u6d4b\u8bd5\\src\\__tests__\\utils\\export-import.test.ts", "source_location": "L55"}, {"id": "utils_export_import_test_mockfile", "label": "mockFile", "file_type": "code", "source_file": "E:\\\u6d4b\u8bd5\\src\\__tests__\\utils\\export-import.test.ts", "source_location": "L211"}, {"id": "utils_export_import_test_data", "label": "data", "file_type": "code", "source_file": "E:\\\u6d4b\u8bd5\\src\\__tests__\\utils\\export-import.test.ts", "source_location": "L306"}, {"id": "utils_export_import_test_backup", "label": "backup", "file_type": "code", "source_file": "E:\\\u6d4b\u8bd5\\src\\__tests__\\utils\\export-import.test.ts", "source_location": "L311"}, {"id": "utils_export_import_test_createobjecturl", "label": "createObjectURL", "file_type": "code", "source_file": "E:\\\u6d4b\u8bd5\\src\\__tests__\\utils\\export-import.test.ts", "source_location": "L345"}, {"id": "utils_export_import_test_revokeobjecturl", "label": "revokeObjectURL", "file_type": "code", "source_file": "E:\\\u6d4b\u8bd5\\src\\__tests__\\utils\\export-import.test.ts", "source_location": "L346"}, {"id": "utils_export_import_test_mockclick", "label": "mockClick", "file_type": "code", "source_file": "E:\\\u6d4b\u8bd5\\src\\__tests__\\utils\\export-import.test.ts", "source_location": "L349"}, {"id": "utils_export_import_test_mocklink", "label": "mockLink", "file_type": "code", "source_file": "E:\\\u6d4b\u8bd5\\src\\__tests__\\utils\\export-import.test.ts", "source_location": "L350"}, {"id": "utils_export_import_test_origcreate", "label": "origCreate", "file_type": "code", "source_file": "E:\\\u6d4b\u8bd5\\src\\__tests__\\utils\\export-import.test.ts", "source_location": "L351"}, {"id": "utils_export_import_test_backupdata", "label": "backupData", "file_type": "code", "source_file": "E:\\\u6d4b\u8bd5\\src\\__tests__\\utils\\export-import.test.ts", "source_location": "L380"}, {"id": "utils_export_import_test_file", "label": "file", "file_type": "code", "source_file": "E:\\\u6d4b\u8bd5\\src\\__tests__\\utils\\export-import.test.ts", "source_location": "L385"}], "edges": [{"source": "e_\u6d4b\u8bd5_src_tests_utils_export_import_test_ts", "target": "vitest", "relation": "imports_from", "context": "import", "confidence": "EXTRACTED", "source_file": "E:\\\u6d4b\u8bd5\\src\\__tests__\\utils\\export-import.test.ts", "source_location": "L1", "weight": 1.0}, {"source": "e_\u6d4b\u8bd5_src_tests_utils_export_import_test_ts", "target": "utils_export_import_test_mockjsontosheet_mockbooknew_mockbookappendsheet_mockwritefile_mockread_mocksheettojson", "relation": "contains", "confidence": "EXTRACTED", "source_file": "E:\\\u6d4b\u8bd5\\src\\__tests__\\utils\\export-import.test.ts", "source_location": "L6", "weight": 1.0}, {"source": "e_\u6d4b\u8bd5_src_tests_utils_export_import_test_ts", "target": "e_\u6d4b\u8bd5_src_utils_export_import_ts", "relation": "imports_from", "context": "import", "confidence": "EXTRACTED", "source_file": "E:\\\u6d4b\u8bd5\\src\\__tests__\\utils\\export-import.test.ts", "source_location": "L33", "weight": 1.0}, {"source": "e_\u6d4b\u8bd5_src_tests_utils_export_import_test_ts", "target": "utils_export_import_exporttoexcel", "relation": "imports", "context": "import", "confidence": "EXTRACTED", "source_file": "E:\\\u6d4b\u8bd5\\src\\__tests__\\utils\\export-import.test.ts", "source_location": "L33", "weight": 1.0}, {"source": "e_\u6d4b\u8bd5_src_tests_utils_export_import_test_ts", "target": "utils_export_import_exportprojects", "relation": "imports", "context": "import", "confidence": "EXTRACTED", "source_file": "E:\\\u6d4b\u8bd5\\src\\__tests__\\utils\\export-import.test.ts", "source_location": "L33", "weight": 1.0}, {"source": "e_\u6d4b\u8bd5_src_tests_utils_export_import_test_ts", "target": "utils_export_import_exportpartners", "relation": "imports", "context": "import", "confidence": "EXTRACTED", "source_file": "E:\\\u6d4b\u8bd5\\src\\__tests__\\utils\\export-import.test.ts", "source_location": "L33", "weight": 1.0}, {"source": "e_\u6d4b\u8bd5_src_tests_utils_export_import_test_ts", "target": "utils_export_import_exportmembers", "relation": "imports", "context": "import", "confidence": "EXTRACTED", "source_file": "E:\\\u6d4b\u8bd5\\src\\__tests__\\utils\\export-import.test.ts", "source_location": "L33", "weight": 1.0}, {"source": "e_\u6d4b\u8bd5_src_tests_utils_export_import_test_ts", "target": "utils_export_import_exportcontracts", "relation": "imports", "context": "import", "confidence": "EXTRACTED", "source_file": "E:\\\u6d4b\u8bd5\\src\\__tests__\\utils\\export-import.test.ts", "source_location": "L33", "weight": 1.0}, {"source": "e_\u6d4b\u8bd5_src_tests_utils_export_import_test_ts", "target": "utils_export_import_exportsettlements", "relation": "imports", "context": "import", "confidence": "EXTRACTED", "source_file": "E:\\\u6d4b\u8bd5\\src\\__tests__\\utils\\export-import.test.ts", "source_location": "L33", "weight": 1.0}, {"source": "e_\u6d4b\u8bd5_src_tests_utils_export_import_test_ts", "target": "utils_export_import_exportinvoices", "relation": "imports", "context": "import", "confidence": "EXTRACTED", "source_file": "E:\\\u6d4b\u8bd5\\src\\__tests__\\utils\\export-import.test.ts", "source_location": "L33", "weight": 1.0}, {"source": "e_\u6d4b\u8bd5_src_tests_utils_export_import_test_ts", "target": "utils_export_import_exportinventory", "relation": "imports", "context": "import", "confidence": "EXTRACTED", "source_file": "E:\\\u6d4b\u8bd5\\src\\__tests__\\utils\\export-import.test.ts", "source_location": "L33", "weight": 1.0}, {"source": "e_\u6d4b\u8bd5_src_tests_utils_export_import_test_ts", "target": "utils_export_import_importfromexcel", "relation": "imports", "context": "import", "confidence": "EXTRACTED", "source_file": "E:\\\u6d4b\u8bd5\\src\\__tests__\\utils\\export-import.test.ts", "source_location": "L33", "weight": 1.0}, {"source": "e_\u6d4b\u8bd5_src_tests_utils_export_import_test_ts", "target": "utils_export_import_importprojects", "relation": "imports", "context": "import", "confidence": "EXTRACTED", "source_file": "E:\\\u6d4b\u8bd5\\src\\__tests__\\utils\\export-import.test.ts", "source_location": "L33", "weight": 1.0}, {"source": "e_\u6d4b\u8bd5_src_tests_utils_export_import_test_ts", "target": "utils_export_import_importpartners", "relation": "imports", "context": "import", "confidence": "EXTRACTED", "source_file": "E:\\\u6d4b\u8bd5\\src\\__tests__\\utils\\export-import.test.ts", "source_location": "L33", "weight": 1.0}, {"source": "e_\u6d4b\u8bd5_src_tests_utils_export_import_test_ts", "target": "utils_export_import_importmembers", "relation": "imports", "context": "import", "confidence": "EXTRACTED", "source_file": "E:\\\u6d4b\u8bd5\\src\\__tests__\\utils\\export-import.test.ts", "source_location": "L33", "weight": 1.0}, {"source": "e_\u6d4b\u8bd5_src_tests_utils_export_import_test_ts", "target": "utils_export_import_createbackupdata", "relation": "imports", "context": "import", "confidence": "EXTRACTED", "source_file": "E:\\\u6d4b\u8bd5\\src\\__tests__\\utils\\export-import.test.ts", "source_location": "L33", "weight": 1.0}, {"source": "e_\u6d4b\u8bd5_src_tests_utils_export_import_test_ts", "target": "utils_export_import_exportbackup", "relation": "imports", "context": "import", "confidence": "EXTRACTED", "source_file": "E:\\\u6d4b\u8bd5\\src\\__tests__\\utils\\export-import.test.ts", "source_location": "L33", "weight": 1.0}, {"source": "e_\u6d4b\u8bd5_src_tests_utils_export_import_test_ts", "target": "utils_export_import_importbackup", "relation": "imports", "context": "import", "confidence": "EXTRACTED", "source_file": "E:\\\u6d4b\u8bd5\\src\\__tests__\\utils\\export-import.test.ts", "source_location": "L33", "weight": 1.0}, {"source": "e_\u6d4b\u8bd5_src_tests_utils_export_import_test_ts", "target": "e_\u6d4b\u8bd5_src_utils_export_import_ts", "relation": "imports_from", "context": "import", "confidence": "EXTRACTED", "source_file": "E:\\\u6d4b\u8bd5\\src\\__tests__\\utils\\export-import.test.ts", "source_location": "L50", "weight": 1.0}, {"source": "e_\u6d4b\u8bd5_src_tests_utils_export_import_test_ts", "target": "utils_export_import_backupdata", "relation": "imports", "context": "import", "confidence": "EXTRACTED", "source_file": "E:\\\u6d4b\u8bd5\\src\\__tests__\\utils\\export-import.test.ts", "source_location": "L50", "weight": 1.0}, {"source": "e_\u6d4b\u8bd5_src_tests_utils_export_import_test_ts", "target": "utils_export_import_test_getcallargs", "relation": "contains", "confidence": "EXTRACTED", "source_file": "E:\\\u6d4b\u8bd5\\src\\__tests__\\utils\\export-import.test.ts", "source_location": "L55", "weight": 1.0}, {"source": "e_\u6d4b\u8bd5_src_tests_utils_export_import_test_ts", "target": "utils_export_import_test_mockfile", "relation": "contains", "confidence": "EXTRACTED", "source_file": "E:\\\u6d4b\u8bd5\\src\\__tests__\\utils\\export-import.test.ts", "source_location": "L211", "weight": 1.0}, {"source": "e_\u6d4b\u8bd5_src_tests_utils_export_import_test_ts", "target": "utils_export_import_test_mockfile", "relation": "contains", "confidence": "EXTRACTED", "source_file": "E:\\\u6d4b\u8bd5\\src\\__tests__\\utils\\export-import.test.ts", "source_location": "L230", "weight": 1.0}, {"source": "e_\u6d4b\u8bd5_src_tests_utils_export_import_test_ts", "target": "utils_export_import_test_mockfile", "relation": "contains", "confidence": "EXTRACTED", "source_file": "E:\\\u6d4b\u8bd5\\src\\__tests__\\utils\\export-import.test.ts", "source_location": "L247", "weight": 1.0}, {"source": "e_\u6d4b\u8bd5_src_tests_utils_export_import_test_ts", "target": "utils_export_import_test_mockfile", "relation": "contains", "confidence": "EXTRACTED", "source_file": "E:\\\u6d4b\u8bd5\\src\\__tests__\\utils\\export-import.test.ts", "source_location": "L271", "weight": 1.0}, {"source": "e_\u6d4b\u8bd5_src_tests_utils_export_import_test_ts", "target": "utils_export_import_test_mockfile", "relation": "contains", "confidence": "EXTRACTED", "source_file": "E:\\\u6d4b\u8bd5\\src\\__tests__\\utils\\export-import.test.ts", "source_location": "L283", "weight": 1.0}, {"source": "e_\u6d4b\u8bd5_src_tests_utils_export_import_test_ts", "target": "utils_export_import_test_mockfile", "relation": "contains", "confidence": "EXTRACTED", "source_file": "E:\\\u6d4b\u8bd5\\src\\__tests__\\utils\\export-import.test.ts", "source_location": "L295", "weight": 1.0}, {"source": "e_\u6d4b\u8bd5_src_tests_utils_export_import_test_ts", "target": "utils_export_import_test_data", "relation": "contains", "confidence": "EXTRACTED", "source_file": "E:\\\u6d4b\u8bd5\\src\\__tests__\\utils\\export-import.test.ts", "source_location": "L306", "weight": 1.0}, {"source": "e_\u6d4b\u8bd5_src_tests_utils_export_import_test_ts", "target": "utils_export_import_test_backup", "relation": "contains", "confidence": "EXTRACTED", "source_file": "E:\\\u6d4b\u8bd5\\src\\__tests__\\utils\\export-import.test.ts", "source_location": "L311", "weight": 1.0}, {"source": "e_\u6d4b\u8bd5_src_tests_utils_export_import_test_ts", "target": "utils_export_import_test_backup", "relation": "contains", "confidence": "EXTRACTED", "source_file": "E:\\\u6d4b\u8bd5\\src\\__tests__\\utils\\export-import.test.ts", "source_location": "L320", "weight": 1.0}, {"source": "e_\u6d4b\u8bd5_src_tests_utils_export_import_test_ts", "target": "utils_export_import_test_backup", "relation": "contains", "confidence": "EXTRACTED", "source_file": "E:\\\u6d4b\u8bd5\\src\\__tests__\\utils\\export-import.test.ts", "source_location": "L325", "weight": 1.0}, {"source": "e_\u6d4b\u8bd5_src_tests_utils_export_import_test_ts", "target": "utils_export_import_test_backup", "relation": "contains", "confidence": "EXTRACTED", "source_file": "E:\\\u6d4b\u8bd5\\src\\__tests__\\utils\\export-import.test.ts", "source_location": "L330", "weight": 1.0}, {"source": "e_\u6d4b\u8bd5_src_tests_utils_export_import_test_ts", "target": "utils_export_import_test_backup", "relation": "contains", "confidence": "EXTRACTED", "source_file": "E:\\\u6d4b\u8bd5\\src\\__tests__\\utils\\export-import.test.ts", "source_location": "L335", "weight": 1.0}, {"source": "e_\u6d4b\u8bd5_src_tests_utils_export_import_test_ts", "target": "utils_export_import_test_createobjecturl", "relation": "contains", "confidence": "EXTRACTED", "source_file": "E:\\\u6d4b\u8bd5\\src\\__tests__\\utils\\export-import.test.ts", "source_location": "L345", "weight": 1.0}, {"source": "e_\u6d4b\u8bd5_src_tests_utils_export_import_test_ts", "target": "utils_export_import_test_revokeobjecturl", "relation": "contains", "confidence": "EXTRACTED", "source_file": "E:\\\u6d4b\u8bd5\\src\\__tests__\\utils\\export-import.test.ts", "source_location": "L346", "weight": 1.0}, {"source": "e_\u6d4b\u8bd5_src_tests_utils_export_import_test_ts", "target": "utils_export_import_test_mockclick", "relation": "contains", "confidence": "EXTRACTED", "source_file": "E:\\\u6d4b\u8bd5\\src\\__tests__\\utils\\export-import.test.ts", "source_location": "L349", "weight": 1.0}, {"source": "e_\u6d4b\u8bd5_src_tests_utils_export_import_test_ts", "target": "utils_export_import_test_mocklink", "relation": "contains", "confidence": "EXTRACTED", "source_file": "E:\\\u6d4b\u8bd5\\src\\__tests__\\utils\\export-import.test.ts", "source_location": "L350", "weight": 1.0}, {"source": "e_\u6d4b\u8bd5_src_tests_utils_export_import_test_ts", "target": "utils_export_import_test_origcreate", "relation": "contains", "confidence": "EXTRACTED", "source_file": "E:\\\u6d4b\u8bd5\\src\\__tests__\\utils\\export-import.test.ts", "source_location": "L351", "weight": 1.0}, {"source": "e_\u6d4b\u8bd5_src_tests_utils_export_import_test_ts", "target": "utils_export_import_test_backup", "relation": "contains", "confidence": "EXTRACTED", "source_file": "E:\\\u6d4b\u8bd5\\src\\__tests__\\utils\\export-import.test.ts", "source_location": "L357", "weight": 1.0}, {"source": "e_\u6d4b\u8bd5_src_tests_utils_export_import_test_ts", "target": "utils_export_import_test_backupdata", "relation": "contains", "confidence": "EXTRACTED", "source_file": "E:\\\u6d4b\u8bd5\\src\\__tests__\\utils\\export-import.test.ts", "source_location": "L380", "weight": 1.0}, {"source": "e_\u6d4b\u8bd5_src_tests_utils_export_import_test_ts", "target": "utils_export_import_test_file", "relation": "contains", "confidence": "EXTRACTED", "source_file": "E:\\\u6d4b\u8bd5\\src\\__tests__\\utils\\export-import.test.ts", "source_location": "L385", "weight": 1.0}, {"source": "e_\u6d4b\u8bd5_src_tests_utils_export_import_test_ts", "target": "utils_export_import_test_file", "relation": "contains", "confidence": "EXTRACTED", "source_file": "E:\\\u6d4b\u8bd5\\src\\__tests__\\utils\\export-import.test.ts", "source_location": "L393", "weight": 1.0}, {"source": "e_\u6d4b\u8bd5_src_tests_utils_export_import_test_ts", "target": "utils_export_import_test_file", "relation": "contains", "confidence": "EXTRACTED", "source_file": "E:\\\u6d4b\u8bd5\\src\\__tests__\\utils\\export-import.test.ts", "source_location": "L398", "weight": 1.0}, {"source": "e_\u6d4b\u8bd5_src_tests_utils_export_import_test_ts", "target": "utils_export_import_test_file", "relation": "contains", "confidence": "EXTRACTED", "source_file": "E:\\\u6d4b\u8bd5\\src\\__tests__\\utils\\export-import.test.ts", "source_location": "L406", "weight": 1.0}], "raw_calls": []}