{"nodes": [{"id": "e_\u6d4b\u8bd5_src_utils_format_ts", "label": "format.ts", "file_type": "code", "source_file": "E:\\\u6d4b\u8bd5\\src\\utils\\format.ts", "source_location": "L1"}, {"id": "utils_format_formatmoney", "label": "formatMoney()", "file_type": "code", "source_file": "E:\\\u6d4b\u8bd5\\src\\utils\\format.ts", "source_location": "L8"}, {"id": "utils_format_parsemoney", "label": "parseMoney()", "file_type": "code", "source_file": "E:\\\u6d4b\u8bd5\\src\\utils\\format.ts", "source_location": "L16"}, {"id": "utils_format_formatpercent", "label": "formatPercent()", "file_type": "code", "source_file": "E:\\\u6d4b\u8bd5\\src\\utils\\format.ts", "source_location": "L24"}, {"id": "utils_format_truncate", "label": "truncate()", "file_type": "code", "source_file": "E:\\\u6d4b\u8bd5\\src\\utils\\format.ts", "source_location": "L32"}, {"id": "utils_format_capitalize", "label": "capitalize()", "file_type": "code", "source_file": "E:\\\u6d4b\u8bd5\\src\\utils\\format.ts", "source_location": "L40"}, {"id": "utils_format_kebabcase", "label": "kebabCase()", "file_type": "code", "source_file": "E:\\\u6d4b\u8bd5\\src\\utils\\format.ts", "source_location": "L48"}, {"id": "utils_format_camelcase", "label": "camelCase()", "file_type": "code", "source_file": "E:\\\u6d4b\u8bd5\\src\\utils\\format.ts", "source_location": "L55"}, {"id": "utils_format_generateid", "label": "generateId()", "file_type": "code", "source_file": "E:\\\u6d4b\u8bd5\\src\\utils\\format.ts", "source_location": "L62"}, {"id": "utils_format_copytoclipboard", "label": "copyToClipboard()", "file_type": "code", "source_file": "E:\\\u6d4b\u8bd5\\src\\utils\\format.ts", "source_location": "L69"}, {"id": "utils_format_downloadfile", "label": "downloadFile()", "file_type": "code", "source_file": "E:\\\u6d4b\u8bd5\\src\\utils\\format.ts", "source_location": "L81"}], "edges": [{"source": "e_\u6d4b\u8bd5_src_utils_format_ts", "target": "utils_format_formatmoney", "relation": "contains", "confidence": "EXTRACTED", "source_file": "E:\\\u6d4b\u8bd5\\src\\utils\\format.ts", "source_location": "L8", "weight": 1.0}, {"source": "e_\u6d4b\u8bd5_src_utils_format_ts", "target": "utils_format_parsemoney", "relation": "contains", "confidence": "EXTRACTED", "source_file": "E:\\\u6d4b\u8bd5\\src\\utils\\format.ts", "source_location": "L16", "weight": 1.0}, {"source": "e_\u6d4b\u8bd5_src_utils_format_ts", "target": "utils_format_formatpercent", "relation": "contains", "confidence": "EXTRACTED", "source_file": "E:\\\u6d4b\u8bd5\\src\\utils\\format.ts", "source_location": "L24", "weight": 1.0}, {"source": "e_\u6d4b\u8bd5_src_utils_format_ts", "target": "utils_format_truncate", "relation": "contains", "confidence": "EXTRACTED", "source_file": "E:\\\u6d4b\u8bd5\\src\\utils\\format.ts", "source_location": "L32", "weight": 1.0}, {"source": "e_\u6d4b\u8bd5_src_utils_format_ts", "target": "utils_format_capitalize", "relation": "contains", "confidence": "EXTRACTED", "source_file": "E:\\\u6d4b\u8bd5\\src\\utils\\format.ts", "source_location": "L40", "weight": 1.0}, {"source": "e_\u6d4b\u8bd5_src_utils_format_ts", "target": "utils_format_kebabcase", "relation": "contains", "confidence": "EXTRACTED", "source_file": "E:\\\u6d4b\u8bd5\\src\\utils\\format.ts", "source_location": "L48", "weight": 1.0}, {"source": "e_\u6d4b\u8bd5_src_utils_format_ts", "target": "utils_format_camelcase", "relation": "contains", "confidence": "EXTRACTED", "source_file": "E:\\\u6d4b\u8bd5\\src\\utils\\format.ts", "source_location": "L55", "weight": 1.0}, {"source": "e_\u6d4b\u8bd5_src_utils_format_ts", "target": "utils_format_generateid", "relation": "contains", "confidence": "EXTRACTED", "source_file": "E:\\\u6d4b\u8bd5\\src\\utils\\format.ts", "source_location": "L62", "weight": 1.0}, {"source": "e_\u6d4b\u8bd5_src_utils_format_ts", "target": "utils_format_copytoclipboard", "relation": "contains", "confidence": "EXTRACTED", "source_file": "E:\\\u6d4b\u8bd5\\src\\utils\\format.ts", "source_location": "L69", "weight": 1.0}, {"source": "e_\u6d4b\u8bd5_src_utils_format_ts", "target": "utils_format_downloadfile", "relation": "contains", "confidence": "EXTRACTED", "source_file": "E:\\\u6d4b\u8bd5\\src\\utils\\format.ts", "source_location": "L81", "weight": 1.0}], "raw_calls": [{"caller_nid": "utils_format_formatmoney", "callee": "replace", "is_member_call": true, "source_file": "E:\\\u6d4b\u8bd5\\src\\utils\\format.ts", "source_location": "L10"}, {"caller_nid": "utils_format_formatmoney", "callee": "toFixed", "is_member_call": true, "source_file": "E:\\\u6d4b\u8bd5\\src\\utils\\format.ts", "source_location": "L10"}, {"caller_nid": "utils_format_parsemoney", "callee": "parseFloat", "is_member_call": false, "source_file": "E:\\\u6d4b\u8bd5\\src\\utils\\format.ts", "source_location": "L18"}, {"caller_nid": "utils_format_parsemoney", "callee": "replace", "is_member_call": true, "source_file": "E:\\\u6d4b\u8bd5\\src\\utils\\format.ts", "source_location": "L18"}, {"caller_nid": "utils_format_formatpercent", "callee": "toFixed", "is_member_call": true, "source_file": "E:\\\u6d4b\u8bd5\\src\\utils\\format.ts", "source_location": "L26"}, {"caller_nid": "utils_format_truncate", "callee": "slice", "is_member_call": true, "source_file": "E:\\\u6d4b\u8bd5\\src\\utils\\format.ts", "source_location": "L34"}, {"caller_nid": "utils_format_capitalize", "callee": "toUpperCase", "is_member_call": true, "source_file": "E:\\\u6d4b\u8bd5\\src\\utils\\format.ts", "source_location": "L42"}, {"caller_nid": "utils_format_capitalize", "callee": "charAt", "is_member_call": true, "source_file": "E:\\\u6d4b\u8bd5\\src\\utils\\format.ts", "source_location": "L42"}, {"caller_nid": "utils_format_capitalize", "callee": "toLowerCase", "is_member_call": true, "source_file": "E:\\\u6d4b\u8bd5\\src\\utils\\format.ts", "source_location": "L42"}, {"caller_nid": "utils_format_capitalize", "callee": "slice", "is_member_call": true, "source_file": "E:\\\u6d4b\u8bd5\\src\\utils\\format.ts", "source_location": "L42"}, {"caller_nid": "utils_format_kebabcase", "callee": "toLowerCase", "is_member_call": true, "source_file": "E:\\\u6d4b\u8bd5\\src\\utils\\format.ts", "source_location": "L49"}, {"caller_nid": "utils_format_kebabcase", "callee": "replace", "is_member_call": true, "source_file": "E:\\\u6d4b\u8bd5\\src\\utils\\format.ts", "source_location": "L49"}, {"caller_nid": "utils_format_camelcase", "callee": "replace", "is_member_call": true, "source_file": "E:\\\u6d4b\u8bd5\\src\\utils\\format.ts", "source_location": "L56"}, {"caller_nid": "utils_format_generateid", "callee": "now", "is_member_call": true, "source_file": "E:\\\u6d4b\u8bd5\\src\\utils\\format.ts", "source_location": "L63"}, {"caller_nid": "utils_format_generateid", "callee": "substr", "is_member_call": true, "source_file": "E:\\\u6d4b\u8bd5\\src\\utils\\format.ts", "source_location": "L63"}, {"caller_nid": "utils_format_generateid", "callee": "toString", "is_member_call": true, "source_file": "E:\\\u6d4b\u8bd5\\src\\utils\\format.ts", "source_location": "L63"}, {"caller_nid": "utils_format_generateid", "callee": "random", "is_member_call": true, "source_file": "E:\\\u6d4b\u8bd5\\src\\utils\\format.ts", "source_location": "L63"}, {"caller_nid": "utils_format_copytoclipboard", "callee": "writeText", "is_member_call": true, "source_file": "E:\\\u6d4b\u8bd5\\src\\utils\\format.ts", "source_location": "L71"}, {"caller_nid": "utils_format_downloadfile", "callee": "createObjectURL", "is_member_call": true, "source_file": "E:\\\u6d4b\u8bd5\\src\\utils\\format.ts", "source_location": "L83"}, {"caller_nid": "utils_format_downloadfile", "callee": "createElement", "is_member_call": true, "source_file": "E:\\\u6d4b\u8bd5\\src\\utils\\format.ts", "source_location": "L84"}, {"caller_nid": "utils_format_downloadfile", "callee": "appendChild", "is_member_call": true, "source_file": "E:\\\u6d4b\u8bd5\\src\\utils\\format.ts", "source_location": "L87"}, {"caller_nid": "utils_format_downloadfile", "callee": "click", "is_member_call": true, "source_file": "E:\\\u6d4b\u8bd5\\src\\utils\\format.ts", "source_location": "L88"}, {"caller_nid": "utils_format_downloadfile", "callee": "removeChild", "is_member_call": true, "source_file": "E:\\\u6d4b\u8bd5\\src\\utils\\format.ts", "source_location": "L89"}, {"caller_nid": "utils_format_downloadfile", "callee": "revokeObjectURL", "is_member_call": true, "source_file": "E:\\\u6d4b\u8bd5\\src\\utils\\format.ts", "source_location": "L90"}]}