{"nodes": [{"id": "e_\u6d4b\u8bd5_src_components_ui_modal_modal_tsx", "label": "Modal.tsx", "file_type": "code", "source_file": "E:\\\u6d4b\u8bd5\\src\\components\\ui\\Modal\\Modal.tsx", "source_location": "L1"}, {"id": "modal_modal_modalsize", "label": "ModalSize", "file_type": "code", "source_file": "E:\\\u6d4b\u8bd5\\src\\components\\ui\\Modal\\Modal.tsx", "source_location": "L6"}, {"id": "modal_modal_modalprops", "label": "ModalProps", "file_type": "code", "source_file": "E:\\\u6d4b\u8bd5\\src\\components\\ui\\Modal\\Modal.tsx", "source_location": "L8"}, {"id": "modal_modal_sizestyles", "label": "sizeStyles", "file_type": "code", "source_file": "E:\\\u6d4b\u8bd5\\src\\components\\ui\\Modal\\Modal.tsx", "source_location": "L23"}, {"id": "modal_modal_overlayvariants", "label": "overlayVariants", "file_type": "code", "source_file": "E:\\\u6d4b\u8bd5\\src\\components\\ui\\Modal\\Modal.tsx", "source_location": "L31"}, {"id": "modal_modal_modalvariants", "label": "modalVariants", "file_type": "code", "source_file": "E:\\\u6d4b\u8bd5\\src\\components\\ui\\Modal\\Modal.tsx", "source_location": "L36"}, {"id": "modal_modal_modal", "label": "Modal()", "file_type": "code", "source_file": "E:\\\u6d4b\u8bd5\\src\\components\\ui\\Modal\\Modal.tsx", "source_location": "L41"}], "edges": [{"source": "e_\u6d4b\u8bd5_src_components_ui_modal_modal_tsx", "target": "react", "relation": "imports_from", "context": "import", "confidence": "EXTRACTED", "source_file": "E:\\\u6d4b\u8bd5\\src\\components\\ui\\Modal\\Modal.tsx", "source_location": "L1", "weight": 1.0}, {"source": "e_\u6d4b\u8bd5_src_components_ui_modal_modal_tsx", "target": "react_dom", "relation": "imports_from", "context": "import", "confidence": "EXTRACTED", "source_file": "E:\\\u6d4b\u8bd5\\src\\components\\ui\\Modal\\Modal.tsx", "source_location": "L2", "weight": 1.0}, {"source": "e_\u6d4b\u8bd5_src_components_ui_modal_modal_tsx", "target": "framer_motion", "relation": "imports_from", "context": "import", "confidence": "EXTRACTED", "source_file": "E:\\\u6d4b\u8bd5\\src\\components\\ui\\Modal\\Modal.tsx", "source_location": "L3", "weight": 1.0}, {"source": "e_\u6d4b\u8bd5_src_components_ui_modal_modal_tsx", "target": "e_\u6d4b\u8bd5_src_components_ui_icon_tsx", "relation": "imports_from", "context": "import", "confidence": "EXTRACTED", "source_file": "E:\\\u6d4b\u8bd5\\src\\components\\ui\\Modal\\Modal.tsx", "source_location": "L4", "weight": 1.0}, {"source": "e_\u6d4b\u8bd5_src_components_ui_modal_modal_tsx", "target": "ui_icon_icon", "relation": "imports", "context": "import", "confidence": "EXTRACTED", "source_file": "E:\\\u6d4b\u8bd5\\src\\components\\ui\\Modal\\Modal.tsx", "source_location": "L4", "weight": 1.0}, {"source": "e_\u6d4b\u8bd5_src_components_ui_modal_modal_tsx", "target": "modal_modal_modalsize", "relation": "contains", "confidence": "EXTRACTED", "source_file": "E:\\\u6d4b\u8bd5\\src\\components\\ui\\Modal\\Modal.tsx", "source_location": "L6", "weight": 1.0}, {"source": "e_\u6d4b\u8bd5_src_components_ui_modal_modal_tsx", "target": "modal_modal_modalprops", "relation": "contains", "confidence": "EXTRACTED", "source_file": "E:\\\u6d4b\u8bd5\\src\\components\\ui\\Modal\\Modal.tsx", "source_location": "L8", "weight": 1.0}, {"source": "e_\u6d4b\u8bd5_src_components_ui_modal_modal_tsx", "target": "modal_modal_sizestyles", "relation": "contains", "confidence": "EXTRACTED", "source_file": "E:\\\u6d4b\u8bd5\\src\\components\\ui\\Modal\\Modal.tsx", "source_location": "L23", "weight": 1.0}, {"source": "e_\u6d4b\u8bd5_src_components_ui_modal_modal_tsx", "target": "modal_modal_overlayvariants", "relation": "contains", "confidence": "EXTRACTED", "source_file": "E:\\\u6d4b\u8bd5\\src\\components\\ui\\Modal\\Modal.tsx", "source_location": "L31", "weight": 1.0}, {"source": "e_\u6d4b\u8bd5_src_components_ui_modal_modal_tsx", "target": "modal_modal_modalvariants", "relation": "contains", "confidence": "EXTRACTED", "source_file": "E:\\\u6d4b\u8bd5\\src\\components\\ui\\Modal\\Modal.tsx", "source_location": "L36", "weight": 1.0}, {"source": "e_\u6d4b\u8bd5_src_components_ui_modal_modal_tsx", "target": "modal_modal_modal", "relation": "contains", "confidence": "EXTRACTED", "source_file": "E:\\\u6d4b\u8bd5\\src\\components\\ui\\Modal\\Modal.tsx", "source_location": "L41", "weight": 1.0}], "raw_calls": [{"caller_nid": "modal_modal_modal", "callee": "useCallback", "is_member_call": false, "source_file": "E:\\\u6d4b\u8bd5\\src\\components\\ui\\Modal\\Modal.tsx", "source_location": "L55"}, {"caller_nid": "modal_modal_modal", "callee": "useEffect", "is_member_call": false, "source_file": "E:\\\u6d4b\u8bd5\\src\\components\\ui\\Modal\\Modal.tsx", "source_location": "L61"}, {"caller_nid": "modal_modal_modal", "callee": "useEffect", "is_member_call": false, "source_file": "E:\\\u6d4b\u8bd5\\src\\components\\ui\\Modal\\Modal.tsx", "source_location": "L66"}, {"caller_nid": "modal_modal_modal", "callee": "createPortal", "is_member_call": false, "source_file": "E:\\\u6d4b\u8bd5\\src\\components\\ui\\Modal\\Modal.tsx", "source_location": "L83"}]}