{"nodes": [{"id": "e_\u6d4b\u8bd5_electron_sqlite_queries_roles_ts", "label": "roles.ts", "file_type": "code", "source_file": "E:\\\u6d4b\u8bd5\\electron\\sqlite\\queries\\roles.ts", "source_location": "L1"}, {"id": "queries_roles_role_columns", "label": "ROLE_COLUMNS", "file_type": "code", "source_file": "E:\\\u6d4b\u8bd5\\electron\\sqlite\\queries\\roles.ts", "source_location": "L15"}, {"id": "queries_roles_listroles", "label": "listRoles()", "file_type": "code", "source_file": "E:\\\u6d4b\u8bd5\\electron\\sqlite\\queries\\roles.ts", "source_location": "L28"}, {"id": "queries_roles_getrolepermissions", "label": "getRolePermissions()", "file_type": "code", "source_file": "E:\\\u6d4b\u8bd5\\electron\\sqlite\\queries\\roles.ts", "source_location": "L42"}, {"id": "queries_roles_updaterolepermissions", "label": "updateRolePermissions()", "file_type": "code", "source_file": "E:\\\u6d4b\u8bd5\\electron\\sqlite\\queries\\roles.ts", "source_location": "L65"}, {"id": "queries_roles_resetrolepermissions", "label": "resetRolePermissions()", "file_type": "code", "source_file": "E:\\\u6d4b\u8bd5\\electron\\sqlite\\queries\\roles.ts", "source_location": "L82"}], "edges": [{"source": "e_\u6d4b\u8bd5_electron_sqlite_queries_roles_ts", "target": "electron_log", "relation": "imports_from", "context": "import", "confidence": "EXTRACTED", "source_file": "E:\\\u6d4b\u8bd5\\electron\\sqlite\\queries\\roles.ts", "source_location": "L8", "weight": 1.0}, {"source": "e_\u6d4b\u8bd5_electron_sqlite_queries_roles_ts", "target": "e_\u6d4b\u8bd5_electron_sqlite_queries_helpers_ts", "relation": "imports_from", "context": "import", "confidence": "EXTRACTED", "source_file": "E:\\\u6d4b\u8bd5\\electron\\sqlite\\queries\\roles.ts", "source_location": "L9", "weight": 1.0}, {"source": "e_\u6d4b\u8bd5_electron_sqlite_queries_roles_ts", "target": "queries_helpers_trygetsqlite", "relation": "imports", "context": "import", "confidence": "EXTRACTED", "source_file": "E:\\\u6d4b\u8bd5\\electron\\sqlite\\queries\\roles.ts", "source_location": "L9", "weight": 1.0}, {"source": "e_\u6d4b\u8bd5_electron_sqlite_queries_roles_ts", "target": "queries_helpers_rowtocamel", "relation": "imports", "context": "import", "confidence": "EXTRACTED", "source_file": "E:\\\u6d4b\u8bd5\\electron\\sqlite\\queries\\roles.ts", "source_location": "L9", "weight": 1.0}, {"source": "e_\u6d4b\u8bd5_electron_sqlite_queries_roles_ts", "target": "queries_helpers_tosqlitevalue", "relation": "imports", "context": "import", "confidence": "EXTRACTED", "source_file": "E:\\\u6d4b\u8bd5\\electron\\sqlite\\queries\\roles.ts", "source_location": "L9", "weight": 1.0}, {"source": "e_\u6d4b\u8bd5_electron_sqlite_queries_roles_ts", "target": "queries_roles_role_columns", "relation": "contains", "confidence": "EXTRACTED", "source_file": "E:\\\u6d4b\u8bd5\\electron\\sqlite\\queries\\roles.ts", "source_location": "L15", "weight": 1.0}, {"source": "e_\u6d4b\u8bd5_electron_sqlite_queries_roles_ts", "target": "queries_roles_listroles", "relation": "contains", "confidence": "EXTRACTED", "source_file": "E:\\\u6d4b\u8bd5\\electron\\sqlite\\queries\\roles.ts", "source_location": "L28", "weight": 1.0}, {"source": "e_\u6d4b\u8bd5_electron_sqlite_queries_roles_ts", "target": "queries_roles_getrolepermissions", "relation": "contains", "confidence": "EXTRACTED", "source_file": "E:\\\u6d4b\u8bd5\\electron\\sqlite\\queries\\roles.ts", "source_location": "L42", "weight": 1.0}, {"source": "e_\u6d4b\u8bd5_electron_sqlite_queries_roles_ts", "target": "queries_roles_updaterolepermissions", "relation": "contains", "confidence": "EXTRACTED", "source_file": "E:\\\u6d4b\u8bd5\\electron\\sqlite\\queries\\roles.ts", "source_location": "L65", "weight": 1.0}, {"source": "e_\u6d4b\u8bd5_electron_sqlite_queries_roles_ts", "target": "queries_roles_resetrolepermissions", "relation": "contains", "confidence": "EXTRACTED", "source_file": "E:\\\u6d4b\u8bd5\\electron\\sqlite\\queries\\roles.ts", "source_location": "L82", "weight": 1.0}], "raw_calls": [{"caller_nid": "queries_roles_listroles", "callee": "tryGetSqlite", "is_member_call": false, "source_file": "E:\\\u6d4b\u8bd5\\electron\\sqlite\\queries\\roles.ts", "source_location": "L29"}, {"caller_nid": "queries_roles_listroles", "callee": "all", "is_member_call": true, "source_file": "E:\\\u6d4b\u8bd5\\electron\\sqlite\\queries\\roles.ts", "source_location": "L33"}, {"caller_nid": "queries_roles_listroles", "callee": "prepare", "is_member_call": true, "source_file": "E:\\\u6d4b\u8bd5\\electron\\sqlite\\queries\\roles.ts", "source_location": "L33"}, {"caller_nid": "queries_roles_listroles", "callee": "map", "is_member_call": true, "source_file": "E:\\\u6d4b\u8bd5\\electron\\sqlite\\queries\\roles.ts", "source_location": "L34"}, {"caller_nid": "queries_roles_listroles", "callee": "error", "is_member_call": true, "source_file": "E:\\\u6d4b\u8bd5\\electron\\sqlite\\queries\\roles.ts", "source_location": "L36"}, {"caller_nid": "queries_roles_getrolepermissions", "callee": "tryGetSqlite", "is_member_call": false, "source_file": "E:\\\u6d4b\u8bd5\\electron\\sqlite\\queries\\roles.ts", "source_location": "L43"}, {"caller_nid": "queries_roles_getrolepermissions", "callee": "get", "is_member_call": true, "source_file": "E:\\\u6d4b\u8bd5\\electron\\sqlite\\queries\\roles.ts", "source_location": "L47"}, {"caller_nid": "queries_roles_getrolepermissions", "callee": "prepare", "is_member_call": true, "source_file": "E:\\\u6d4b\u8bd5\\electron\\sqlite\\queries\\roles.ts", "source_location": "L47"}, {"caller_nid": "queries_roles_getrolepermissions", "callee": "parse", "is_member_call": true, "source_file": "E:\\\u6d4b\u8bd5\\electron\\sqlite\\queries\\roles.ts", "source_location": "L50"}, {"caller_nid": "queries_roles_getrolepermissions", "callee": "error", "is_member_call": true, "source_file": "E:\\\u6d4b\u8bd5\\electron\\sqlite\\queries\\roles.ts", "source_location": "L55"}, {"caller_nid": "queries_roles_updaterolepermissions", "callee": "tryGetSqlite", "is_member_call": false, "source_file": "E:\\\u6d4b\u8bd5\\electron\\sqlite\\queries\\roles.ts", "source_location": "L66"}, {"caller_nid": "queries_roles_updaterolepermissions", "callee": "run", "is_member_call": true, "source_file": "E:\\\u6d4b\u8bd5\\electron\\sqlite\\queries\\roles.ts", "source_location": "L70"}, {"caller_nid": "queries_roles_updaterolepermissions", "callee": "prepare", "is_member_call": true, "source_file": "E:\\\u6d4b\u8bd5\\electron\\sqlite\\queries\\roles.ts", "source_location": "L70"}, {"caller_nid": "queries_roles_updaterolepermissions", "callee": "stringify", "is_member_call": true, "source_file": "E:\\\u6d4b\u8bd5\\electron\\sqlite\\queries\\roles.ts", "source_location": "L71"}, {"caller_nid": "queries_roles_updaterolepermissions", "callee": "error", "is_member_call": true, "source_file": "E:\\\u6d4b\u8bd5\\electron\\sqlite\\queries\\roles.ts", "source_location": "L76"}, {"caller_nid": "queries_roles_resetrolepermissions", "callee": "tryGetSqlite", "is_member_call": false, "source_file": "E:\\\u6d4b\u8bd5\\electron\\sqlite\\queries\\roles.ts", "source_location": "L83"}, {"caller_nid": "queries_roles_resetrolepermissions", "callee": "run", "is_member_call": true, "source_file": "E:\\\u6d4b\u8bd5\\electron\\sqlite\\queries\\roles.ts", "source_location": "L87"}, {"caller_nid": "queries_roles_resetrolepermissions", "callee": "prepare", "is_member_call": true, "source_file": "E:\\\u6d4b\u8bd5\\electron\\sqlite\\queries\\roles.ts", "source_location": "L87"}, {"caller_nid": "queries_roles_resetrolepermissions", "callee": "stringify", "is_member_call": true, "source_file": "E:\\\u6d4b\u8bd5\\electron\\sqlite\\queries\\roles.ts", "source_location": "L88"}, {"caller_nid": "queries_roles_resetrolepermissions", "callee": "error", "is_member_call": true, "source_file": "E:\\\u6d4b\u8bd5\\electron\\sqlite\\queries\\roles.ts", "source_location": "L93"}]}