{"nodes": [{"id": "e_\u6d4b\u8bd5_scripts_create_seed_data_js", "label": "create-seed-data.js", "file_type": "code", "source_file": "E:\\\u6d4b\u8bd5\\scripts\\create-seed-data.js", "source_location": "L1"}, {"id": "scripts_create_seed_data_fs", "label": "fs", "file_type": "code", "source_file": "E:\\\u6d4b\u8bd5\\scripts\\create-seed-data.js", "source_location": "L5"}, {"id": "scripts_create_seed_data_path", "label": "path", "file_type": "code", "source_file": "E:\\\u6d4b\u8bd5\\scripts\\create-seed-data.js", "source_location": "L6"}, {"id": "scripts_create_seed_data_dest", "label": "DEST", "file_type": "code", "source_file": "E:\\\u6d4b\u8bd5\\scripts\\create-seed-data.js", "source_location": "L9"}, {"id": "scripts_create_seed_data_data", "label": "data", "file_type": "code", "source_file": "E:\\\u6d4b\u8bd5\\scripts\\create-seed-data.js", "source_location": "L11"}, {"id": "scripts_create_seed_data_base64_fields", "label": "BASE64_FIELDS", "file_type": "code", "source_file": "E:\\\u6d4b\u8bd5\\scripts\\create-seed-data.js", "source_location": "L14"}, {"id": "scripts_create_seed_data_fake_names", "label": "FAKE_NAMES", "file_type": "code", "source_file": "E:\\\u6d4b\u8bd5\\scripts\\create-seed-data.js", "source_location": "L24"}, {"id": "scripts_create_seed_data_fake_phones", "label": "FAKE_PHONES", "file_type": "code", "source_file": "E:\\\u6d4b\u8bd5\\scripts\\create-seed-data.js", "source_location": "L25"}, {"id": "scripts_create_seed_data_fake_idcards", "label": "FAKE_IDCARDS", "file_type": "code", "source_file": "E:\\\u6d4b\u8bd5\\scripts\\create-seed-data.js", "source_location": "L26"}, {"id": "scripts_create_seed_data_fake_addresses", "label": "FAKE_ADDRESSES", "file_type": "code", "source_file": "E:\\\u6d4b\u8bd5\\scripts\\create-seed-data.js", "source_location": "L27"}, {"id": "scripts_create_seed_data_nextfakename", "label": "nextFakeName()", "file_type": "code", "source_file": "E:\\\u6d4b\u8bd5\\scripts\\create-seed-data.js", "source_location": "L31"}, {"id": "scripts_create_seed_data_nextfakephone", "label": "nextFakePhone()", "file_type": "code", "source_file": "E:\\\u6d4b\u8bd5\\scripts\\create-seed-data.js", "source_location": "L32"}, {"id": "scripts_create_seed_data_nextfakeidcard", "label": "nextFakeIdCard()", "file_type": "code", "source_file": "E:\\\u6d4b\u8bd5\\scripts\\create-seed-data.js", "source_location": "L33"}, {"id": "scripts_create_seed_data_nextfakeaddress", "label": "nextFakeAddress()", "file_type": "code", "source_file": "E:\\\u6d4b\u8bd5\\scripts\\create-seed-data.js", "source_location": "L34"}, {"id": "scripts_create_seed_data_person_name_fields", "label": "PERSON_NAME_FIELDS", "file_type": "code", "source_file": "E:\\\u6d4b\u8bd5\\scripts\\create-seed-data.js", "source_location": "L36"}, {"id": "scripts_create_seed_data_person_phone_fields", "label": "PERSON_PHONE_FIELDS", "file_type": "code", "source_file": "E:\\\u6d4b\u8bd5\\scripts\\create-seed-data.js", "source_location": "L39"}, {"id": "scripts_create_seed_data_person_id_fields", "label": "PERSON_ID_FIELDS", "file_type": "code", "source_file": "E:\\\u6d4b\u8bd5\\scripts\\create-seed-data.js", "source_location": "L42"}, {"id": "scripts_create_seed_data_person_addr_fields", "label": "PERSON_ADDR_FIELDS", "file_type": "code", "source_file": "E:\\\u6d4b\u8bd5\\scripts\\create-seed-data.js", "source_location": "L45"}, {"id": "scripts_create_seed_data_stripbase64", "label": "stripBase64()", "file_type": "code", "source_file": "E:\\\u6d4b\u8bd5\\scripts\\create-seed-data.js", "source_location": "L49"}, {"id": "scripts_create_seed_data_cleaned", "label": "cleaned", "file_type": "code", "source_file": "E:\\\u6d4b\u8bd5\\scripts\\create-seed-data.js", "source_location": "L97"}, {"id": "scripts_create_seed_data_seed", "label": "seed", "file_type": "code", "source_file": "E:\\\u6d4b\u8bd5\\scripts\\create-seed-data.js", "source_location": "L101"}, {"id": "scripts_create_seed_data_now", "label": "NOW", "file_type": "code", "source_file": "E:\\\u6d4b\u8bd5\\scripts\\create-seed-data.js", "source_location": "L103"}, {"id": "scripts_create_seed_data_fresh", "label": "fresh", "file_type": "code", "source_file": "E:\\\u6d4b\u8bd5\\scripts\\create-seed-data.js", "source_location": "L109"}, {"id": "scripts_create_seed_data_json", "label": "json", "file_type": "code", "source_file": "E:\\\u6d4b\u8bd5\\scripts\\create-seed-data.js", "source_location": "L120"}, {"id": "scripts_create_seed_data_kb", "label": "kb", "file_type": "code", "source_file": "E:\\\u6d4b\u8bd5\\scripts\\create-seed-data.js", "source_location": "L122"}], "edges": [{"source": "e_\u6d4b\u8bd5_scripts_create_seed_data_js", "target": "fs", "relation": "imports_from", "context": "import", "confidence": "EXTRACTED", "source_file": "E:\\\u6d4b\u8bd5\\scripts\\create-seed-data.js", "source_location": "L5", "weight": 1.0}, {"source": "e_\u6d4b\u8bd5_scripts_create_seed_data_js", "target": "scripts_create_seed_data_fs", "relation": "contains", "confidence": "EXTRACTED", "source_file": "E:\\\u6d4b\u8bd5\\scripts\\create-seed-data.js", "source_location": "L5", "weight": 1.0}, {"source": "e_\u6d4b\u8bd5_scripts_create_seed_data_js", "target": "path", "relation": "imports_from", "context": "import", "confidence": "EXTRACTED", "source_file": "E:\\\u6d4b\u8bd5\\scripts\\create-seed-data.js", "source_location": "L6", "weight": 1.0}, {"source": "e_\u6d4b\u8bd5_scripts_create_seed_data_js", "target": "scripts_create_seed_data_path", "relation": "contains", "confidence": "EXTRACTED", "source_file": "E:\\\u6d4b\u8bd5\\scripts\\create-seed-data.js", "source_location": "L6", "weight": 1.0}, {"source": "e_\u6d4b\u8bd5_scripts_create_seed_data_js", "target": "scripts_create_seed_data_dest", "relation": "contains", "confidence": "EXTRACTED", "source_file": "E:\\\u6d4b\u8bd5\\scripts\\create-seed-data.js", "source_location": "L9", "weight": 1.0}, {"source": "e_\u6d4b\u8bd5_scripts_create_seed_data_js", "target": "scripts_create_seed_data_data", "relation": "contains", "confidence": "EXTRACTED", "source_file": "E:\\\u6d4b\u8bd5\\scripts\\create-seed-data.js", "source_location": "L11", "weight": 1.0}, {"source": "e_\u6d4b\u8bd5_scripts_create_seed_data_js", "target": "scripts_create_seed_data_base64_fields", "relation": "contains", "confidence": "EXTRACTED", "source_file": "E:\\\u6d4b\u8bd5\\scripts\\create-seed-data.js", "source_location": "L14", "weight": 1.0}, {"source": "e_\u6d4b\u8bd5_scripts_create_seed_data_js", "target": "scripts_create_seed_data_fake_names", "relation": "contains", "confidence": "EXTRACTED", "source_file": "E:\\\u6d4b\u8bd5\\scripts\\create-seed-data.js", "source_location": "L24", "weight": 1.0}, {"source": "e_\u6d4b\u8bd5_scripts_create_seed_data_js", "target": "scripts_create_seed_data_fake_phones", "relation": "contains", "confidence": "EXTRACTED", "source_file": "E:\\\u6d4b\u8bd5\\scripts\\create-seed-data.js", "source_location": "L25", "weight": 1.0}, {"source": "e_\u6d4b\u8bd5_scripts_create_seed_data_js", "target": "scripts_create_seed_data_fake_idcards", "relation": "contains", "confidence": "EXTRACTED", "source_file": "E:\\\u6d4b\u8bd5\\scripts\\create-seed-data.js", "source_location": "L26", "weight": 1.0}, {"source": "e_\u6d4b\u8bd5_scripts_create_seed_data_js", "target": "scripts_create_seed_data_fake_addresses", "relation": "contains", "confidence": "EXTRACTED", "source_file": "E:\\\u6d4b\u8bd5\\scripts\\create-seed-data.js", "source_location": "L27", "weight": 1.0}, {"source": "e_\u6d4b\u8bd5_scripts_create_seed_data_js", "target": "scripts_create_seed_data_nextfakename", "relation": "contains", "confidence": "EXTRACTED", "source_file": "E:\\\u6d4b\u8bd5\\scripts\\create-seed-data.js", "source_location": "L31", "weight": 1.0}, {"source": "e_\u6d4b\u8bd5_scripts_create_seed_data_js", "target": "scripts_create_seed_data_nextfakephone", "relation": "contains", "confidence": "EXTRACTED", "source_file": "E:\\\u6d4b\u8bd5\\scripts\\create-seed-data.js", "source_location": "L32", "weight": 1.0}, {"source": "e_\u6d4b\u8bd5_scripts_create_seed_data_js", "target": "scripts_create_seed_data_nextfakeidcard", "relation": "contains", "confidence": "EXTRACTED", "source_file": "E:\\\u6d4b\u8bd5\\scripts\\create-seed-data.js", "source_location": "L33", "weight": 1.0}, {"source": "e_\u6d4b\u8bd5_scripts_create_seed_data_js", "target": "scripts_create_seed_data_nextfakeaddress", "relation": "contains", "confidence": "EXTRACTED", "source_file": "E:\\\u6d4b\u8bd5\\scripts\\create-seed-data.js", "source_location": "L34", "weight": 1.0}, {"source": "e_\u6d4b\u8bd5_scripts_create_seed_data_js", "target": "scripts_create_seed_data_person_name_fields", "relation": "contains", "confidence": "EXTRACTED", "source_file": "E:\\\u6d4b\u8bd5\\scripts\\create-seed-data.js", "source_location": "L36", "weight": 1.0}, {"source": "e_\u6d4b\u8bd5_scripts_create_seed_data_js", "target": "scripts_create_seed_data_person_phone_fields", "relation": "contains", "confidence": "EXTRACTED", "source_file": "E:\\\u6d4b\u8bd5\\scripts\\create-seed-data.js", "source_location": "L39", "weight": 1.0}, {"source": "e_\u6d4b\u8bd5_scripts_create_seed_data_js", "target": "scripts_create_seed_data_person_id_fields", "relation": "contains", "confidence": "EXTRACTED", "source_file": "E:\\\u6d4b\u8bd5\\scripts\\create-seed-data.js", "source_location": "L42", "weight": 1.0}, {"source": "e_\u6d4b\u8bd5_scripts_create_seed_data_js", "target": "scripts_create_seed_data_person_addr_fields", "relation": "contains", "confidence": "EXTRACTED", "source_file": "E:\\\u6d4b\u8bd5\\scripts\\create-seed-data.js", "source_location": "L45", "weight": 1.0}, {"source": "e_\u6d4b\u8bd5_scripts_create_seed_data_js", "target": "scripts_create_seed_data_stripbase64", "relation": "contains", "confidence": "EXTRACTED", "source_file": "E:\\\u6d4b\u8bd5\\scripts\\create-seed-data.js", "source_location": "L49", "weight": 1.0}, {"source": "e_\u6d4b\u8bd5_scripts_create_seed_data_js", "target": "scripts_create_seed_data_cleaned", "relation": "contains", "confidence": "EXTRACTED", "source_file": "E:\\\u6d4b\u8bd5\\scripts\\create-seed-data.js", "source_location": "L97", "weight": 1.0}, {"source": "e_\u6d4b\u8bd5_scripts_create_seed_data_js", "target": "scripts_create_seed_data_seed", "relation": "contains", "confidence": "EXTRACTED", "source_file": "E:\\\u6d4b\u8bd5\\scripts\\create-seed-data.js", "source_location": "L101", "weight": 1.0}, {"source": "e_\u6d4b\u8bd5_scripts_create_seed_data_js", "target": "scripts_create_seed_data_now", "relation": "contains", "confidence": "EXTRACTED", "source_file": "E:\\\u6d4b\u8bd5\\scripts\\create-seed-data.js", "source_location": "L103", "weight": 1.0}, {"source": "e_\u6d4b\u8bd5_scripts_create_seed_data_js", "target": "scripts_create_seed_data_fresh", "relation": "contains", "confidence": "EXTRACTED", "source_file": "E:\\\u6d4b\u8bd5\\scripts\\create-seed-data.js", "source_location": "L109", "weight": 1.0}, {"source": "e_\u6d4b\u8bd5_scripts_create_seed_data_js", "target": "scripts_create_seed_data_json", "relation": "contains", "confidence": "EXTRACTED", "source_file": "E:\\\u6d4b\u8bd5\\scripts\\create-seed-data.js", "source_location": "L120", "weight": 1.0}, {"source": "e_\u6d4b\u8bd5_scripts_create_seed_data_js", "target": "scripts_create_seed_data_kb", "relation": "contains", "confidence": "EXTRACTED", "source_file": "E:\\\u6d4b\u8bd5\\scripts\\create-seed-data.js", "source_location": "L122", "weight": 1.0}, {"source": "scripts_create_seed_data_stripbase64", "target": "scripts_create_seed_data_nextfakename", "relation": "calls", "context": "call", "confidence": "EXTRACTED", "source_file": "E:\\\u6d4b\u8bd5\\scripts\\create-seed-data.js", "source_location": "L73", "weight": 1.0}, {"source": "scripts_create_seed_data_stripbase64", "target": "scripts_create_seed_data_nextfakephone", "relation": "calls", "context": "call", "confidence": "EXTRACTED", "source_file": "E:\\\u6d4b\u8bd5\\scripts\\create-seed-data.js", "source_location": "L82", "weight": 1.0}, {"source": "scripts_create_seed_data_stripbase64", "target": "scripts_create_seed_data_nextfakeidcard", "relation": "calls", "context": "call", "confidence": "EXTRACTED", "source_file": "E:\\\u6d4b\u8bd5\\scripts\\create-seed-data.js", "source_location": "L84", "weight": 1.0}, {"source": "scripts_create_seed_data_stripbase64", "target": "scripts_create_seed_data_nextfakeaddress", "relation": "calls", "context": "call", "confidence": "EXTRACTED", "source_file": "E:\\\u6d4b\u8bd5\\scripts\\create-seed-data.js", "source_location": "L86", "weight": 1.0}], "raw_calls": [{"caller_nid": "scripts_create_seed_data_stripbase64", "callee": "isArray", "is_member_call": true, "source_file": "E:\\\u6d4b\u8bd5\\scripts\\create-seed-data.js", "source_location": "L50"}, {"caller_nid": "scripts_create_seed_data_stripbase64", "callee": "map", "is_member_call": true, "source_file": "E:\\\u6d4b\u8bd5\\scripts\\create-seed-data.js", "source_location": "L51"}, {"caller_nid": "scripts_create_seed_data_stripbase64", "callee": "entries", "is_member_call": true, "source_file": "E:\\\u6d4b\u8bd5\\scripts\\create-seed-data.js", "source_location": "L55"}, {"caller_nid": "scripts_create_seed_data_stripbase64", "callee": "has", "is_member_call": true, "source_file": "E:\\\u6d4b\u8bd5\\scripts\\create-seed-data.js", "source_location": "L56"}, {"caller_nid": "scripts_create_seed_data_stripbase64", "callee": "isArray", "is_member_call": true, "source_file": "E:\\\u6d4b\u8bd5\\scripts\\create-seed-data.js", "source_location": "L57"}, {"caller_nid": "scripts_create_seed_data_stripbase64", "callee": "map", "is_member_call": true, "source_file": "E:\\\u6d4b\u8bd5\\scripts\\create-seed-data.js", "source_location": "L58"}, {"caller_nid": "scripts_create_seed_data_stripbase64", "callee": "startsWith", "is_member_call": true, "source_file": "E:\\\u6d4b\u8bd5\\scripts\\create-seed-data.js", "source_location": "L63"}, {"caller_nid": "scripts_create_seed_data_stripbase64", "callee": "startsWith", "is_member_call": true, "source_file": "E:\\\u6d4b\u8bd5\\scripts\\create-seed-data.js", "source_location": "L68"}, {"caller_nid": "scripts_create_seed_data_stripbase64", "callee": "has", "is_member_call": true, "source_file": "E:\\\u6d4b\u8bd5\\scripts\\create-seed-data.js", "source_location": "L70"}, {"caller_nid": "scripts_create_seed_data_stripbase64", "callee": "has", "is_member_call": true, "source_file": "E:\\\u6d4b\u8bd5\\scripts\\create-seed-data.js", "source_location": "L81"}, {"caller_nid": "scripts_create_seed_data_stripbase64", "callee": "has", "is_member_call": true, "source_file": "E:\\\u6d4b\u8bd5\\scripts\\create-seed-data.js", "source_location": "L83"}, {"caller_nid": "scripts_create_seed_data_stripbase64", "callee": "has", "is_member_call": true, "source_file": "E:\\\u6d4b\u8bd5\\scripts\\create-seed-data.js", "source_location": "L85"}]}